verilog/rtl_converted/reg_cell.v
module reg_cell (
	clk,
	rst_n,
	we,
	oe,
	d,
	out
);
	parameter signed [31:0] W = 8;
	parameter [W - 1:0] RESET_VALUE = 1'sb0;
	input wire clk;
	input wire rst_n;
	input wire we;
	input wire oe;
	input wire [W - 1:0] d;
	output wire [W - 1:0] out;
	reg [W - 1:0] reg_q;
	always @(posedge clk or negedge rst_n)
		if (~rst_n)
			reg_q <= RESET_VALUE;
		else if (we)
			reg_q <= d;
	assign out = (oe ? reg_q : {W {1'sb0}});
endmodule

verilog/sim/unit/tb_reg_cell.sv
`timescale 1ns/1ps

module tb_reg_cell;

    localparam int W = 8;

    logic clk;
    logic rst_n;
    logic we;
    logic oe;
    logic [W-1:0] d;
    logic [W-1:0] out;

    reg_cell #(.W(W), .RESET_VALUE('0)) dut (
        .clk  (clk),
        .rst_n(rst_n),
        .we   (we),
        .oe   (oe),
        .d    (d),
        .out  (out)
    );

    initial clk = 0;
    always #5 clk <= ~clk;

    task tick;
        @(posedge clk);
        #1; 
    endtask

    

    initial begin
        rst_n = 1;
        we    = 0;
        oe    = 1;
        d     = '0;

        // write test
        d  = 8'hAB;
        we = 1;
        tick();
        if (out !== 8'hAB) $fatal(1, "write AB failed. out=%h", out);

        // async reset test
        rst_n = 0;       
        #1;              
        if (out !== 8'h00) $fatal(1, "async reset failed. out=%h", out);

        rst_n = 1;    
        #1;

        // 2) we=0 hold test
        we = 0;
        d  = 8'h55;
        tick();
        if (out !== 8'h00) $fatal(1, "hold failed. out=%h", out);

        // 3) write test
        we = 1;
        d  = 8'h12;
        tick();
        if (out !== 8'h12) $fatal(1, "write 12 failed. out=%h", out);

        d  = 8'h34;
        tick();
        if (out !== 8'h34) $fatal(1, "write 34 failed. out=%h", out);

        // 4) oe gating
        oe = 0;
        #1;
        if (out !== 8'h00) $fatal(1, "oe=0 gating failed. out=%h", out);

        oe = 1;
        #1;
        if (out !== 8'h34) $fatal(1, "oe=1 ungate failed. out=%h", out);

        $display("PASS: tb_reg_cell OK");
        $finish;
    end

    initial begin
        $dumpfile("wave.vcd");
        $dumpvars(0, tb_reg_cell);
    end
endmodule

verilog/wave.vcd
$version Generated by VerilatedVcd $end
$timescale 1ps $end
 $scope module TOP $end
  $scope module tb_reg_cell $end
   $var wire 32 * W [31:0] $end
   $var wire 1 # clk $end
   $var wire 1 $ rst_n $end
   $var wire 1 % we $end
   $var wire 1 & oe $end
   $var wire 8 ' d [7:0] $end
   $var wire 8 ( out [7:0] $end
   $scope module dut $end
    $var wire 32 * W [31:0] $end
    $var wire 8 + RESET_VALUE [7:0] $end
    $var wire 1 # clk $end
    $var wire 1 $ rst_n $end
    $var wire 1 % we $end
    $var wire 1 & oe $end
    $var wire 8 ' d [7:0] $end
    $var wire 8 ( out [7:0] $end
    $var wire 8 ) reg_q [7:0] $end
   $upscope $end
  $upscope $end
 $upscope $end
$enddefinitions $end


#0
0#
1$
1%
1&
b10101011 '
b00000000 (
b00000000 )
b00000000000000000000000000001000 *
b00000000 +
#5000
1#
b10101011 (
b10101011 )
#6000
0$
b00000000 (
b00000000 )
#7000
1$
#8000
0%
b01010101 '
#10000
0#
#15000
1#
#16000
1%
b00010010 '
#20000
0#
#25000
1#
b00010010 (
b00010010 )
#26000
b00110100 '
#30000
0#
#35000
1#
b00110100 (
b00110100 )
#36000
0&
b00000000 (
#37000
1&
b00110100 (
